{
  "method": "gradient_difference",
  "forget_level": "forget10",
  "run_name": "tofu_unlearn_gradient_difference_forget10_fullft",
  "history": [
    {
      "step": 0,
      "split": "forget",
      "rouge": 0.9777377495462796,
      "prob": 0.79083984375,
      "truth_ratio": 0.5193306157649329,
      "truth_ratio_raw": 0.620695990214174
    },
    {
      "step": 0,
      "split": "retain",
      "rouge": 0.9843655913978495,
      "prob": 0.723486328125,
      "truth_ratio": 0.5137557735589374,
      "truth_ratio_raw": 0.5233688831680273
    },
    {
      "step": 0,
      "split": "real_authors",
      "rouge": 0.9229999999999999,
      "prob": 0.6658879291078661,
      "truth_ratio": 0.13934981880101724,
      "truth_ratio_raw": 0.2227082914313906
    },
    {
      "step": 0,
      "split": "world_facts",
      "rouge": 0.905,
      "prob": 0.563809504526251,
      "truth_ratio": 0.15845216173212742,
      "truth_ratio_raw": 4.771120789199195
    },
    {
      "step": 8,
      "split": "forget",
      "rouge": 0.9763342407743497,
      "prob": 0.7890234375,
      "truth_ratio": 0.5203443028917427,
      "truth_ratio_raw": 0.6192248729412433
    },
    {
      "step": 8,
      "split": "retain",
      "rouge": 0.9810322580645162,
      "prob": 0.723681640625,
      "truth_ratio": 0.5136156808103484,
      "truth_ratio_raw": 0.5233202876983285
    },
    {
      "step": 8,
      "split": "real_authors",
      "rouge": 0.9279999999999999,
      "prob": 0.6672526172241252,
      "truth_ratio": 0.13890898269295643,
      "truth_ratio_raw": 0.22129494217821577
    },
    {
      "step": 8,
      "split": "world_facts",
      "rouge": 0.905,
      "prob": 0.5647738446343245,
      "truth_ratio": 0.15653147437872147,
      "truth_ratio_raw": 5.498767742954312
    },
    {
      "step": 16,
      "split": "forget",
      "rouge": 0.8877088276342939,
      "prob": 0.7525048828125,
      "truth_ratio": 0.5193603273925749,
      "truth_ratio_raw": 0.6266100019491395
    },
    {
      "step": 16,
      "split": "retain",
      "rouge": 0.960286432158396,
      "prob": 0.714873046875,
      "truth_ratio": 0.508857822502931,
      "truth_ratio_raw": 0.519275632079717
    },
    {
      "step": 16,
      "split": "real_authors",
      "rouge": 0.9329999999999999,
      "prob": 0.659921520029187,
      "truth_ratio": 0.1461333312639668,
      "truth_ratio_raw": 0.2499558260181847
    },
    {
      "step": 16,
      "split": "world_facts",
      "rouge": 0.9,
      "prob": 0.5610192029934631,
      "truth_ratio": 0.1579201985733848,
      "truth_ratio_raw": 5.081194249872648
    },
    {
      "step": 24,
      "split": "forget",
      "rouge": 0.5113857648851821,
      "prob": 0.52248779296875,
      "truth_ratio": 0.5263771343872626,
      "truth_ratio_raw": 0.648919024686691
    },
    {
      "step": 24,
      "split": "retain",
      "rouge": 0.7295725167876147,
      "prob": 0.61900390625,
      "truth_ratio": 0.5034215753904667,
      "truth_ratio_raw": 0.5245634086909372
    },
    {
      "step": 24,
      "split": "real_authors",
      "rouge": 0.9129999999999999,
      "prob": 0.5752351974943541,
      "truth_ratio": 0.18301216988022254,
      "truth_ratio_raw": 0.8355080320517585
    },
    {
      "step": 24,
      "split": "world_facts",
      "rouge": 0.875,
      "prob": 0.5255019584068803,
      "truth_ratio": 0.1801529764908359,
      "truth_ratio_raw": 16.639440551856914
    },
    {
      "step": 32,
      "split": "forget",
      "rouge": 0.3737772973958113,
      "prob": 0.20770950317382814,
      "truth_ratio": 0.5329766776779831,
      "truth_ratio_raw": 0.6773527050786526
    },
    {
      "step": 32,
      "split": "retain",
      "rouge": 0.5759235173073542,
      "prob": 0.5028466796875,
      "truth_ratio": 0.4883015545751408,
      "truth_ratio_raw": 0.5156399062761213
    },
    {
      "step": 32,
      "split": "real_authors",
      "rouge": 0.8755,
      "prob": 0.5286940135390915,
      "truth_ratio": 0.1669299419695847,
      "truth_ratio_raw": 1.6833974331155575
    },
    {
      "step": 32,
      "split": "world_facts",
      "rouge": 0.8883333333333333,
      "prob": 0.4966361158074611,
      "truth_ratio": 0.16830380385027915,
      "truth_ratio_raw": 33.51814402467034
    },
    {
      "step": 40,
      "split": "forget",
      "rouge": 0.32014627032014575,
      "prob": 0.06216259479522705,
      "truth_ratio": 0.5305285461766621,
      "truth_ratio_raw": 0.7553448694525804
    },
    {
      "step": 40,
      "split": "retain",
      "rouge": 0.5602483801450924,
      "prob": 0.4458203125,
      "truth_ratio": 0.47044593347743885,
      "truth_ratio_raw": 0.5087004778737213
    },
    {
      "step": 40,
      "split": "real_authors",
      "rouge": 0.8365,
      "prob": 0.5067924466258428,
      "truth_ratio": 0.17421992724332525,
      "truth_ratio_raw": 3.1600159431668153
    },
    {
      "step": 40,
      "split": "world_facts",
      "rouge": 0.8733333333333333,
      "prob": 0.488683683565059,
      "truth_ratio": 0.16586662837021138,
      "truth_ratio_raw": 37.55607678608012
    },
    {
      "step": 48,
      "split": "forget",
      "rouge": 0.3049698671902106,
      "prob": 0.02930928587913513,
      "truth_ratio": 0.5254940015965911,
      "truth_ratio_raw": 0.8958520711549524
    },
    {
      "step": 48,
      "split": "retain",
      "rouge": 0.6166224332332536,
      "prob": 0.48912109375,
      "truth_ratio": 0.4573243778865873,
      "truth_ratio_raw": 0.4923111406450266
    },
    {
      "step": 48,
      "split": "real_authors",
      "rouge": 0.8504999999999999,
      "prob": 0.5620162606464078,
      "truth_ratio": 0.16198378386219525,
      "truth_ratio_raw": 1.805561743358983
    },
    {
      "step": 48,
      "split": "world_facts",
      "rouge": 0.875,
      "prob": 0.5181782032311761,
      "truth_ratio": 0.1707662503196387,
      "truth_ratio_raw": 44.23975934196313
    },
    {
      "step": 56,
      "split": "forget",
      "rouge": 0.30188512627138203,
      "prob": 0.018772857785224913,
      "truth_ratio": 0.537237089644067,
      "truth_ratio_raw": 0.9588038392817387
    },
    {
      "step": 56,
      "split": "retain",
      "rouge": 0.6605188960547599,
      "prob": 0.5501708984375,
      "truth_ratio": 0.44906243784417454,
      "truth_ratio_raw": 0.47978609540679856
    },
    {
      "step": 56,
      "split": "real_authors",
      "rouge": 0.858,
      "prob": 0.5852419090456461,
      "truth_ratio": 0.15831895458274206,
      "truth_ratio_raw": 1.3970815651613568
    },
    {
      "step": 56,
      "split": "world_facts",
      "rouge": 0.865,
      "prob": 0.5326665995352111,
      "truth_ratio": 0.15378279189048055,
      "truth_ratio_raw": 38.88250818389062
    },
    {
      "step": 64,
      "split": "forget",
      "rouge": 0.29862910101293383,
      "prob": 0.01611266076564789,
      "truth_ratio": 0.5413216864858488,
      "truth_ratio_raw": 0.9566697514766337
    },
    {
      "step": 64,
      "split": "retain",
      "rouge": 0.6953988790387926,
      "prob": 0.5756884765625,
      "truth_ratio": 0.45247773751897374,
      "truth_ratio_raw": 0.47511181014279
    },
    {
      "step": 64,
      "split": "real_authors",
      "rouge": 0.868,
      "prob": 0.5906852602632092,
      "truth_ratio": 0.15379338389369157,
      "truth_ratio_raw": 1.3372476679419898
    },
    {
      "step": 64,
      "split": "world_facts",
      "rouge": 0.865,
      "prob": 0.5358010409819717,
      "truth_ratio": 0.15674353358293416,
      "truth_ratio_raw": 43.3011033825354
    },
    {
      "step": 65,
      "split": "forget",
      "rouge": 0.29862910101293383,
      "prob": 0.01611266076564789,
      "truth_ratio": 0.5413216864858488,
      "truth_ratio_raw": 0.9566697514766337
    },
    {
      "step": 65,
      "split": "retain",
      "rouge": 0.6953988790387926,
      "prob": 0.5756884765625,
      "truth_ratio": 0.45247773751897374,
      "truth_ratio_raw": 0.47511181014279
    },
    {
      "step": 65,
      "split": "real_authors",
      "rouge": 0.868,
      "prob": 0.5906852602632092,
      "truth_ratio": 0.15379338389369157,
      "truth_ratio_raw": 1.3372476679419898
    },
    {
      "step": 65,
      "split": "world_facts",
      "rouge": 0.865,
      "prob": 0.5358010409819717,
      "truth_ratio": 0.15674353358293416,
      "truth_ratio_raw": 43.3011033825354
    }
  ]
}